CHANGES.rst
CONTRIBUTORS.rst
DEVELOP.rst
LICENSE.rst
MANIFEST.in
README.rst
setup.cfg
setup.py
docs/TODO.txt
src/collective/__init__.py
src/collective.recaptcha.egg-info/PKG-INFO
src/collective.recaptcha.egg-info/SOURCES.txt
src/collective.recaptcha.egg-info/dependency_links.txt
src/collective.recaptcha.egg-info/entry_points.txt
src/collective.recaptcha.egg-info/namespace_packages.txt
src/collective.recaptcha.egg-info/not-zip-safe
src/collective.recaptcha.egg-info/requires.txt
src/collective.recaptcha.egg-info/top_level.txt
src/collective/recaptcha/__init__.py
src/collective/recaptcha/bbb.py
src/collective/recaptcha/configure.zcml
src/collective/recaptcha/settings.py
src/collective/recaptcha/testing.py
src/collective/recaptcha/view.py
src/collective/recaptcha/locales/collective.recaptcha.pot
src/collective/recaptcha/locales/pt_BR/LC_MESSAGES/collective.recaptcha.po
src/collective/recaptcha/profiles/default/controlpanel.xml
src/collective/recaptcha/profiles/default/metadata.xml
src/collective/recaptcha/profiles/default/registry.xml
src/collective/recaptcha/profiles/uninstall/controlpanel.xml
src/collective/recaptcha/profiles/uninstall/registry.xml
src/collective/recaptcha/tests/__init__.py
src/collective/recaptcha/tests/test_settings.py
src/collective/recaptcha/tests/test_setup.py
src/collective/recaptcha/tests/test_view.py