Metadata-Version: 2.1
Name: collective.recaptcha
Version: 2.1.2
Summary: Wraps the recaptcha-client library to provide a drop-in replacement for collective.captcha.
Home-page: https://github.com/collective/collective.recaptcha
Author: David Glick
Author-email: david@glicksoftware.com
License: GPL version 2
Project-URL: Source, https://github.com/collective/collective.recaptcha
Project-URL: Tracker, https://github.com/collective/collective.recaptcha/issues
Project-URL: PyPI, https://pypi.python.org/pypi/collective.recaptcha
Keywords: captcha recaptcha zope Python Plone
Platform: UNKNOWN
Classifier: Environment :: Web Environment
Classifier: Framework :: Plone
Classifier: Framework :: Plone :: Addon
Classifier: Framework :: Plone :: 4.2
Classifier: Framework :: Plone :: 4.3
Classifier: Framework :: Plone :: 5.0
Classifier: Programming Language :: Python
Classifier: Programming Language :: Python :: 2.7
Classifier: Operating System :: OS Independent
Classifier: License :: OSI Approved :: GNU General Public License v2 (GPLv2)
Requires-Python: ==2.7
Provides-Extra: test
